similarity_ts_cli/__init__.py
similarity_ts_cli/cli.py
similarity_ts_cli-1.0.1.dist-info/LICENSE
similarity_ts_cli-1.0.1.dist-info/METADATA
similarity_ts_cli-1.0.1.dist-info/WHEEL
similarity_ts_cli-1.0.1.dist-info/entry_points.txt
similarity_ts_cli-1.0.1.dist-info/top_level.txt
similarity_ts_cli-1.0.1.dist-info/RECORD
