Metadata-Version: 2.1
Name: similarity-ts-cli
Version: 1.0.1
Summary: SimilarityTS-cli is an open-source tool designed to facilitate the usage of SimilarityTS package from a command line interface
Author-email: Alejandro Fernández-Montes <afdez@us.es>, Damián Fernández-Cerero <damiancerero@us.es>, Felipe Escalera González <fescalera@us.es>
Project-URL: Homepage, https://github.com/alejandrofdez-us/similarity-ts-cli
Project-URL: Bug Tracker, https://github.com/alejandrofdez-us/similarity-ts-cli/issues
Classifier: Programming Language :: Python :: 3
Classifier: License :: OSI Approved :: MIT License
Classifier: Operating System :: OS Independent
Requires-Python: >=3.9
License-File: LICENSE
Requires-Dist: similarity-ts
Requires-Dist: tqdm
